{
    "KDE-KIO-Protocols": {
        "trash": {
            "Class": ":local", 
            "ExtraNames": [
                "Original Path", 
                "Deletion Date"
            ], 
            "ExtraTypes": [
                "QString", 
                "QDateTime"
            ], 
            "Icon": "user-trash-full", 
            "copyFromFile": true, 
            "copyToFile": true, 
            "deleteRecursive": true, 
            "deleting": true, 
            "exec": "kf5/kio/trash", 
            "fileNameUsedForCopying": "DisplayName", 
            "input": "none", 
            "linking": false, 
            "listing": [
                "Name", 
                "Type", 
                "Size", 
                "Extra1", 
                "Extra2", 
                "Date", 
                "Access", 
                "Owner", 
                "Group", 
                "Link"
            ], 
            "makedir": false, 
            "maxInstances": 2, 
            "moving": true, 
            "output": "filesystem", 
            "protocol": "trash", 
            "reading": true, 
            "renameFromFile": true, 
            "renameToFile": true, 
            "writing": true
        }
    }
}